{
    "_links": {
        "self": {
            "href": "http:\/\/default\/tags\/%D9%85%D8%AE%D8%A7%D9%88%D9%81-%D8%A7%D9%84%D8%A8%D9%86%D8%AA%D8%A7%D8%BA%D9%88%D9%86?_format=hal_json"
        },
        "type": {
            "href": "http:\/\/drupal.org\/rest\/type\/taxonomy_term\/tags"
        }
    },
    "tid": [
        {
            "value": 52
        }
    ],
    "uuid": [
        {
            "value": "110b7f60-7b01-41cc-8e9a-32360f2a0fd1"
        }
    ],
    "langcode": [
        {
            "value": "ar",
            "lang": "ar"
        }
    ],
    "vid": [
        {
            "target_id": "tags"
        }
    ],
    "name": [
        {
            "value": "\u0645\u062e\u0627\u0648\u0641 \u0627\u0644\u0628\u0646\u062a\u0627\u063a\u0648\u0646",
            "lang": "ar"
        }
    ],
    "weight": [
        {
            "value": 0
        }
    ],
    "changed": [
        {
            "value": 1497877282,
            "lang": "ar"
        }
    ],
    "default_langcode": [
        {
            "value": true,
            "lang": "ar"
        }
    ]
}