{
    "_links": {
        "self": {
            "href": "http:\/\/default\/tags\/india?_format=hal_json"
        },
        "type": {
            "href": "http:\/\/drupal.org\/rest\/type\/taxonomy_term\/tags"
        }
    },
    "tid": [
        {
            "value": 62
        }
    ],
    "uuid": [
        {
            "value": "d985cc6c-466f-4b9f-82ba-c37f0e56cdc0"
        }
    ],
    "langcode": [
        {
            "value": "en",
            "lang": "en"
        }
    ],
    "vid": [
        {
            "target_id": "tags"
        }
    ],
    "name": [
        {
            "value": "India",
            "lang": "en"
        }
    ],
    "weight": [
        {
            "value": 0
        }
    ],
    "changed": [
        {
            "value": 1497944761,
            "lang": "en"
        }
    ],
    "default_langcode": [
        {
            "value": true,
            "lang": "en"
        }
    ]
}