{
    "_links": {
        "self": {
            "href": "http:\/\/default\/media\/39?_format=hal_json"
        },
        "type": {
            "href": "http:\/\/drupal.org\/rest\/type\/media\/image"
        },
        "http:\/\/drupal.org\/rest\/relation\/media\/image\/thumbnail": [
            {
                "href": "http:\/\/default\/sites\/default\/files\/2017-06\/170526150808-venture-capitalist-kirsten-green-we-need-more-women-founders-00011830-1024x576.jpg"
            }
        ],
        "http:\/\/drupal.org\/rest\/relation\/media\/image\/uid": [
            {
                "href": "http:\/\/default\/user\/1?_format=hal_json"
            }
        ],
        "http:\/\/drupal.org\/rest\/relation\/media\/image\/revision_uid": [
            {
                "href": "http:\/\/default\/user\/1?_format=hal_json"
            }
        ],
        "http:\/\/drupal.org\/rest\/relation\/media\/image\/field_image": [
            {
                "href": "http:\/\/default\/sites\/default\/files\/2017-06\/170526150808-venture-capitalist-kirsten-green-we-need-more-women-founders-00011830-1024x576.jpg"
            }
        ]
    },
    "mid": [
        {
            "value": 39
        }
    ],
    "uuid": [
        {
            "value": "86b7f38d-2946-47c8-8c72-188fa1ae7f37"
        }
    ],
    "vid": [
        {
            "value": 39
        }
    ],
    "bundle": [
        {
            "target_id": "image"
        }
    ],
    "langcode": [
        {
            "value": "en",
            "lang": "en"
        }
    ],
    "name": [
        {
            "value": "Walmart is buying Bonobos for $310 million"
        }
    ],
    "_embedded": {
        "http:\/\/drupal.org\/rest\/relation\/media\/image\/thumbnail": [
            {
                "_links": {
                    "self": {
                        "href": "http:\/\/default\/sites\/default\/files\/2017-06\/170526150808-venture-capitalist-kirsten-green-we-need-more-women-founders-00011830-1024x576.jpg"
                    },
                    "type": {
                        "href": "http:\/\/drupal.org\/rest\/type\/file\/file"
                    }
                },
                "uuid": [
                    {
                        "value": "35252997-e6b5-46f0-a666-e12eedaf525b"
                    }
                ],
                "alt": "Thumbnail",
                "title": "Walmart is buying Bonobos for $310 million",
                "width": "1024",
                "height": "576"
            }
        ],
        "http:\/\/drupal.org\/rest\/relation\/media\/image\/uid": [
            {
                "_links": {
                    "self": {
                        "href": "http:\/\/default\/user\/1?_format=hal_json"
                    },
                    "type": {
                        "href": "http:\/\/drupal.org\/rest\/type\/user\/user"
                    }
                },
                "uuid": [
                    {
                        "value": "b7860c21-5c21-4729-ae97-124e602b6718"
                    }
                ]
            }
        ],
        "http:\/\/drupal.org\/rest\/relation\/media\/image\/revision_uid": [
            {
                "_links": {
                    "self": {
                        "href": "http:\/\/default\/user\/1?_format=hal_json"
                    },
                    "type": {
                        "href": "http:\/\/drupal.org\/rest\/type\/user\/user"
                    }
                },
                "uuid": [
                    {
                        "value": "b7860c21-5c21-4729-ae97-124e602b6718"
                    }
                ]
            }
        ],
        "http:\/\/drupal.org\/rest\/relation\/media\/image\/field_image": [
            {
                "_links": {
                    "self": {
                        "href": "http:\/\/default\/sites\/default\/files\/2017-06\/170526150808-venture-capitalist-kirsten-green-we-need-more-women-founders-00011830-1024x576.jpg"
                    },
                    "type": {
                        "href": "http:\/\/drupal.org\/rest\/type\/file\/file"
                    }
                },
                "uuid": [
                    {
                        "value": "35252997-e6b5-46f0-a666-e12eedaf525b"
                    }
                ],
                "alt": "Walmart is buying Bonobos for $310 million",
                "title": "Walmart is buying Bonobos for $310 million",
                "width": "1024",
                "height": "576"
            }
        ]
    },
    "status": [
        {
            "value": true
        }
    ],
    "created": [
        {
            "value": 1497869103
        }
    ],
    "changed": [
        {
            "value": 1497869103
        }
    ],
    "revision_timestamp": [
        {
            "value": 1497869103
        }
    ],
    "default_langcode": [
        {
            "value": true,
            "lang": "en"
        }
    ]
}