{
    "_links": {
        "self": {
            "href": "http:\/\/default\/media\/28?_format=hal_json"
        },
        "type": {
            "href": "http:\/\/drupal.org\/rest\/type\/media\/image"
        },
        "http:\/\/drupal.org\/rest\/relation\/media\/image\/thumbnail": [
            {
                "href": "http:\/\/default\/sites\/default\/files\/2017-06\/170418105933-jon-ossoff-karen-handel-split-exlarge-169.jpg"
            }
        ],
        "http:\/\/drupal.org\/rest\/relation\/media\/image\/uid": [
            {
                "href": "http:\/\/default\/user\/1?_format=hal_json"
            }
        ],
        "http:\/\/drupal.org\/rest\/relation\/media\/image\/revision_uid": [
            {
                "href": "http:\/\/default\/user\/1?_format=hal_json"
            }
        ],
        "http:\/\/drupal.org\/rest\/relation\/media\/image\/field_image": [
            {
                "href": "http:\/\/default\/sites\/default\/files\/2017-06\/170418105933-jon-ossoff-karen-handel-split-exlarge-169.jpg"
            }
        ]
    },
    "mid": [
        {
            "value": 28
        }
    ],
    "uuid": [
        {
            "value": "ee6c86ff-6f5e-4c56-95e4-180d6d4d940e"
        }
    ],
    "vid": [
        {
            "value": 28
        }
    ],
    "bundle": [
        {
            "target_id": "image"
        }
    ],
    "langcode": [
        {
            "value": "en",
            "lang": "en"
        }
    ],
    "name": [
        {
            "value": "Early vote tally foretells soaring turnout in most expensive House race ever"
        }
    ],
    "_embedded": {
        "http:\/\/drupal.org\/rest\/relation\/media\/image\/thumbnail": [
            {
                "_links": {
                    "self": {
                        "href": "http:\/\/default\/sites\/default\/files\/2017-06\/170418105933-jon-ossoff-karen-handel-split-exlarge-169.jpg"
                    },
                    "type": {
                        "href": "http:\/\/drupal.org\/rest\/type\/file\/file"
                    }
                },
                "uuid": [
                    {
                        "value": "88417149-1545-4c39-98d8-a2da0acf68ad"
                    }
                ],
                "alt": "Thumbnail",
                "title": "Early vote tally foretells soaring turnout in most expensive House race ever",
                "width": "780",
                "height": "438"
            }
        ],
        "http:\/\/drupal.org\/rest\/relation\/media\/image\/uid": [
            {
                "_links": {
                    "self": {
                        "href": "http:\/\/default\/user\/1?_format=hal_json"
                    },
                    "type": {
                        "href": "http:\/\/drupal.org\/rest\/type\/user\/user"
                    }
                },
                "uuid": [
                    {
                        "value": "b7860c21-5c21-4729-ae97-124e602b6718"
                    }
                ]
            }
        ],
        "http:\/\/drupal.org\/rest\/relation\/media\/image\/revision_uid": [
            {
                "_links": {
                    "self": {
                        "href": "http:\/\/default\/user\/1?_format=hal_json"
                    },
                    "type": {
                        "href": "http:\/\/drupal.org\/rest\/type\/user\/user"
                    }
                },
                "uuid": [
                    {
                        "value": "b7860c21-5c21-4729-ae97-124e602b6718"
                    }
                ]
            }
        ],
        "http:\/\/drupal.org\/rest\/relation\/media\/image\/field_image": [
            {
                "_links": {
                    "self": {
                        "href": "http:\/\/default\/sites\/default\/files\/2017-06\/170418105933-jon-ossoff-karen-handel-split-exlarge-169.jpg"
                    },
                    "type": {
                        "href": "http:\/\/drupal.org\/rest\/type\/file\/file"
                    }
                },
                "uuid": [
                    {
                        "value": "88417149-1545-4c39-98d8-a2da0acf68ad"
                    }
                ],
                "alt": "Early vote tally foretells soaring turnout in most expensive House race ever",
                "title": "Early vote tally foretells soaring turnout in most expensive House race ever",
                "width": "780",
                "height": "438"
            }
        ]
    },
    "status": [
        {
            "value": true
        }
    ],
    "created": [
        {
            "value": 1497784304
        }
    ],
    "changed": [
        {
            "value": 1497784304
        }
    ],
    "revision_timestamp": [
        {
            "value": 1497784304
        }
    ],
    "default_langcode": [
        {
            "value": true,
            "lang": "en"
        }
    ]
}